[
    {
        "build": "B_8_2_1_004(RELEASE)",
        "error": null,
        "id": 1,
        "lnn": 1,
        "release": "v8.2.1.0",
        "revision": "577025145365856260",
        "status": null,
        "type": "Isilon OneFS",
        "version": "Isilon OneFS v8.2.1.0 B_8_2_1_004(RELEASE): 0x802015000000004:Fri Oct  4 18:07:01 PDT 2019    root@sea-build11-100:/b/mnt/obj/b/mnt/src/amd64.amd64/sys/IQ.amd64.release   FreeBSD clang version 3.9.1 (tags/RELEASE_391/final 289601) (based on LLVM 3.9.1)"
    },
    {
        "build": "B_8_2_1_004(RELEASE)",
        "error": null,
        "id": 2,
        "lnn": 2,
        "release": "v8.2.1.0",
        "revision": "577025145365856260",
        "status": null,
        "type": "Isilon OneFS",
        "version": "Isilon OneFS v8.2.1.0 B_8_2_1_004(RELEASE): 0x802015000000004:Fri Oct  4 18:07:01 PDT 2019    root@sea-build11-100:/b/mnt/obj/b/mnt/src/amd64.amd64/sys/IQ.amd64.release   FreeBSD clang version 3.9.1 (tags/RELEASE_391/final 289601) (based on LLVM 3.9.1)"
    },
    {
        "build": "B_8_2_1_004(RELEASE)",
        "error": null,
        "id": 3,
        "lnn": 3,
        "release": "v8.2.1.0",
        "revision": "577025145365856260",
        "status": null,
        "type": "Isilon OneFS",
        "version": "Isilon OneFS v8.2.1.0 B_8_2_1_004(RELEASE): 0x802015000000004:Fri Oct  4 18:07:01 PDT 2019    root@sea-build11-100:/b/mnt/obj/b/mnt/src/amd64.amd64/sys/IQ.amd64.release   FreeBSD clang version 3.9.1 (tags/RELEASE_391/final 289601) (based on LLVM 3.9.1)"
    },
    {
        "build": "B_8_2_1_004(RELEASE)",
        "error": null,
        "id": 4,
        "lnn": 4,
        "release": "v8.2.1.0",
        "revision": "577025145365856260",
        "status": null,
        "type": "Isilon OneFS",
        "version": "Isilon OneFS v8.2.1.0 B_8_2_1_004(RELEASE): 0x802015000000004:Fri Oct  4 18:07:01 PDT 2019    root@sea-build11-100:/b/mnt/obj/b/mnt/src/amd64.amd64/sys/IQ.amd64.release   FreeBSD clang version 3.9.1 (tags/RELEASE_391/final 289601) (based on LLVM 3.9.1)"
    }
]